{
  "forge_marker": 1,
  "defaults": {
    "model": "itech:item/generated"
  },
  "variants": {
    "dull": {
      "chunk": {
        "textures": {"layer0": "itech:items/materialsets/dull/chunk", "layer1": "itech:items/materialsets/dull/overlays/chunk"}
      },
      "crushed": {
        "textures": {"layer0": "itech:items/materialsets/dull/crushed", "layer1": "itech:items/materialsets/dull/overlays/crushed"}
      },
      "crushedcentrifuged": {
        "textures": {"layer0": "itech:items/materialsets/dull/crushedcentrifuged"}
      },
      "crushedpurified": {
        "textures": {"layer0": "itech:items/materialsets/dull/crushedpurified"}
      },
      "dust": {
        "textures": {"layer0": "itech:items/materialsets/dull/dust"}
      },
      "dustsmall": {
        "textures": {"layer0": "itech:items/materialsets/dull/dustsmall"}
      },
      "dusttiny": {
        "textures": {"layer0": "itech:items/materialsets/dull/dusttiny"}
      },
      "nugget": {
        "textures": {"layer0": "itech:items/materialsets/dull/nugget"}
      },
      "ingot": {
        "textures": {"layer0": "itech:items/materialsets/dull/ingot"}
      },
      "ingothot": {
        "textures": {"layer0": "itech:items/materialsets/dull/ingothot"}
      },
      "plate": {
        "textures": {"layer0": "itech:items/materialsets/dull/plate"}
      },
      "platedense": {
        "textures": {"layer0": "itech:items/materialsets/dull/platedense"}
      },
      "foil": {
        "textures": {"layer0": "itech:items/materialsets/dull/foil"}
      },
      "rod": {
        "textures": {"layer0": "itech:items/materialsets/dull/rod"}
      },
      "bolt": {
        "textures": {"layer0": "itech:items/materialsets/dull/bolt"}
      },
      "screw": {
        "textures": {"layer0": "itech:items/materialsets/dull/screw"}
      },
      "ring": {
        "textures": {"layer0": "itech:items/materialsets/dull/ring"}
      },
      "spring": {
        "textures": {"layer0": "itech:items/materialsets/dull/spring"}
      },
      "wirefine": {
        "textures": {"layer0": "itech:items/materialsets/dull/wirefine"}
      },
      "rotor": {
        "textures": {"layer0": "itech:items/materialsets/dull/rotor"}
      },
      "gear": {
        "textures": {"layer0": "itech:items/materialsets/dull/gear"}
      },
      "gearsmall": {
        "textures": {"layer0": "itech:items/materialsets/dull/gearsmall"}
      },
      "lens": {
        "textures": {"layer0": "itech:items/materialsets/dull/lens"}
      },
      "cell": {
        "textures": {"layer0": "itech:items/materialsets/dull/overlays/cell", "layer1": "itech:items/materialsets/dull/cell"}
      },
      "cellplasma": {
        "textures": {"layer0": "itech:items/materialsets/dull/overlays/cellplasma", "layer1": "itech:items/materialsets/dull/cellplasma"}
      }
    }
  }
}